main.py
analyse_wb_senegal/__init__.py
analyse_wb_senegal/analyse_wb_senegal.py
analyse_wb_senegal/api.py
analyse_wb_senegal/cli.py
analyse_wb_senegal-0.1.1.dist-info/licenses/AUTHORS.rst
analyse_wb_senegal-0.1.1.dist-info/licenses/LICENSE
analyse_wb_senegal-0.1.1.dist-info/METADATA
analyse_wb_senegal-0.1.1.dist-info/WHEEL
analyse_wb_senegal-0.1.1.dist-info/top_level.txt
analyse_wb_senegal-0.1.1.dist-info/RECORD
