Metadata-Version: 2.4
Name: analyse_wb_senegal
Version: 0.1.1
Summary: Analyse de donnees economiques du Senegal avec l'API World Bank
Author-email: Leopold Dieng <dieng.leopold@gmail.com>
Maintainer-email: Leopold Dieng <dieng.leopold@gmail.com>
License: MIT license
Project-URL: bugs, https://github.com/dienglord/analyse_wb_senegal/issues
Project-URL: changelog, https://github.com/dienglord/analyse_wb_senegal/blob/master/changelog.md
Project-URL: homepage, https://github.com/dienglord/analyse_wb_senegal
License-File: LICENSE
License-File: AUTHORS.rst
Requires-Dist: requests
Requires-Dist: pandas
Provides-Extra: dev
Requires-Dist: coverage; extra == "dev"
Requires-Dist: mypy; extra == "dev"
Requires-Dist: pytest; extra == "dev"
Requires-Dist: ruff; extra == "dev"
Dynamic: license-file
